utils_repl/__init__.py
utils_repl-0.1.0.dist-info/METADATA
utils_repl-0.1.0.dist-info/WHEEL
utils_repl-0.1.0.dist-info/RECORD
